genome/__init__.py
genome/admin.py
genome/app_settings.py
genome/apps.py
genome/choices.py
genome/filters.py
genome/managers.py
genome/models.py
genome/serializers.py
genome/urls.py
genome/utils.py
genome/views.py
genome/viewsets.py
genome/management/__init__.py
genome/management/commands/__init__.py
genome/management/commands/genome_sync.py
genome/management/commands/preferred_transcript_sync.py
genome/migrations/0001_initial.py
genome/migrations/0002_auto_20180330_0837.py
genome/migrations/0003_auto_20180601_0901.py
genome/migrations/0004_preferred_transcripts.py
genome/migrations/0005_add_important_gene_dates.py
genome/migrations/0006_gene_symbol_unique.py
genome/migrations/__init__.py
django_genome-1.1.1.dist-info/AUTHORS.rst
django_genome-1.1.1.dist-info/LICENSE
django_genome-1.1.1.dist-info/METADATA
django_genome-1.1.1.dist-info/WHEEL
django_genome-1.1.1.dist-info/top_level.txt
django_genome-1.1.1.dist-info/RECORD
