Metadata-Version: 2.1
Name: django-genome
Version: 1.1.1
Summary: Django app for syncing and storing human genome reference data
Home-page: https://github.com/genomics-geek/django-genome
Author: Michael A. Gonzalez
Author-email: GonzalezMA@email.chop.edu
License: MIT
Keywords: django-genome
Platform: UNKNOWN
Classifier: Development Status :: 5 - Production/Stable
Classifier: Framework :: Django :: 2.0
Classifier: Framework :: Django :: 2.1
Classifier: Framework :: Django :: 2.2
Classifier: Intended Audience :: Developers
Classifier: License :: OSI Approved :: BSD License
Classifier: Natural Language :: English
Classifier: Programming Language :: Python :: 3
Classifier: Programming Language :: Python :: 3.5
Classifier: Programming Language :: Python :: 3.6
Requires-Dist: djangorestframework (==3.10.3)
Requires-Dist: django-filter (==2.2.0)
Requires-Dist: django-genomix (==1.1.0)
Requires-Dist: django-model-utils (==3.2.0)
Requires-Dist: mysqlclient (==1.4.4)
Requires-Dist: tqdm (==4.37.0)
